polyswarm_api/__init__.py
polyswarm_api/api.py
polyswarm_api/core.py
polyswarm_api/exceptions.py
polyswarm_api/resources.py
polyswarm_api/settings.py
polyswarm_api-3.14.1.dist-info/licenses/LICENSE
polyswarm_api-3.14.1.dist-info/METADATA
polyswarm_api-3.14.1.dist-info/WHEEL
polyswarm_api-3.14.1.dist-info/top_level.txt
polyswarm_api-3.14.1.dist-info/RECORD
