Metadata-Version: 2.4
Name: polyswarm_api
Version: 3.14.1
Summary: Client library to simplify interacting with the PolySwarm consumer API
Author-email: PolySwarm Developers <info@polyswarm.io>
License: MIT
Project-URL: Homepage, https://github.com/polyswarm/polyswarm-api
Classifier: Intended Audience :: Developers
Classifier: License :: OSI Approved :: MIT License
Classifier: Operating System :: OS Independent
Classifier: Programming Language :: Python :: 3.10
Classifier: Programming Language :: Python :: 3.11
Classifier: Programming Language :: Python :: 3.12
Requires-Python: <4,>=3.10
License-File: LICENSE
Requires-Dist: requests>=2.31
Requires-Dist: python-dateutil>=2.9
Provides-Extra: tests
Requires-Dist: bump-my-version~=1.2; extra == "tests"
Requires-Dist: pytest~=7.4; extra == "tests"
Requires-Dist: jsonschema~=3.0.2; extra == "tests"
Requires-Dist: responses~=0.23.3; extra == "tests"
Requires-Dist: python-dateutil~=2.9.0; extra == "tests"
Requires-Dist: vcrpy~=7.0; extra == "tests"
Dynamic: license-file
